MANIFEST.in
README.md
setup.py
stf/__init__.py
stf.egg-info/PKG-INFO
stf.egg-info/SOURCES.txt
stf.egg-info/dependency_links.txt
stf.egg-info/not-zip-safe
stf.egg-info/requires.txt
stf.egg-info/top_level.txt
stf/bin/iniParser.py
stf/bin/stf
stf/examples/feature1/cf.ini
stf/examples/feature1/stf__UT__CSFTST-10/s5__script__runtest1
stf/examples/feature1/stf__UT__CSFTST-9/s5__script__runtest2
stf/examples/feature1/stf__function__CSFTST-11/s10__script__runstep2
stf/examples/feature1/stf__function__CSFTST-11/s15__script~ainet@testlab4__runtest1
stf/examples/feature1/stf__function__CSFTST-11/s16__script__runtest2
stf/examples/feature1/stf__function__CSFTST-7/s5__script~ainet@testlab4__runtest1
stf/examples/feature1/stf__function__CSFTST-8/s5__script__runtest3
stf/examples/feature1/stf__security__CSFTST-12/s5__script__runtest3
stf/examples/feature1/stf__setup/s5__script__precheckLabEnv
stf/examples/feature1/stf__teardown/s5__script__precheckLabEnv
stf/examples/feature2/stf.ini
stf/examples/feature2/CSFMSGPRTL-183/stfs1__script~lab__func__fs0346
stf/examples/feature2/CSFMSGPRTL-183/stfs1__script~lab__func__fs0369
stf/examples/feature2/CSFMSGPRTL-183/stfs1__script~lab__func__fs3821
stf/examples/feature2/CSFMSGPRTL-183/stfs1__script~lab__func__fs3826
stf/examples/feature2/CSFMSGPRTL-183/stfs1__script~lab__func__fs3853
stf/examples/feature2/CSFMSGPRTL-183/stfs1__script~lab__func__fs3859
stf/examples/feature2/CSFMSGPRTL-183/stf__setup/s10__script~lab__build
stf/examples/feature2/CSFMSGPRTL-183/stf__setup/s5__copy~lab__rawmsg
stf/examples/feature2/CSFMSGPRTL-183/stf__teardown/s10__script~lab__clean
stf/examples/feature2/upload_files/artifactory.repo
stf/examples/feature2/upload_files/raw_msg/fs0346.msg
stf/examples/feature2/upload_files/raw_msg/fs0346RR.msg
stf/examples/feature2/upload_files/raw_msg/fs0369.msg
stf/examples/feature2/upload_files/raw_msg/fs0369RR.msg
stf/examples/feature2/upload_files/raw_msg/fs3821.msg
stf/examples/feature2/upload_files/raw_msg/fs3821RR.msg
stf/examples/feature2/upload_files/raw_msg/fs3826.msg
stf/examples/feature2/upload_files/raw_msg/fs3826RR.msg
stf/examples/feature2/upload_files/raw_msg/fs3853.msg
