Metadata-Version: 1.1
Name: stf
Version: 0.2.4
Summary: The simple test framework
Home-page: https://github.com/nokia
Author: Gemfield
Author-email: gemfield@civilnet.cn
License: Apache License, Version 2.0
Download-URL: https://github.com/nokia/STF/archive/0.2.4.tar.gz
Keywords: automation test
Platform: UNKNOWN
Classifier: Programming Language :: Python
Classifier: Programming Language :: Python :: 2
Classifier: Topic :: Software Development :: Testing
